{
    "id": 2829934992,
    "number": 1566,
    "title": "[Bug]: Sorry, something went wrong, please try again",
    "body": "### Can you reproduce this bug in the PWA?\n\nNot applicable\n\n### Describe the bug\n\nUnable to use team in brower,deb apk or chrome desktop extensions or any browser in my ubuntu 24.04 version\n\n### What package are you using?\n\ndeb\n\n### Version\n\n1.12.6\n\n### Reproduction steps\n\n```markdown\n1.In ubuntu 24.04 try to open teams in anywhere\n2.After the sign in or sign up page the page changes to Sorry, something went wrong, please try again\n3.it will tell to restart or switch to different account but nothing works\n...\n```\n\n### Expected Behavior\n\n```markdown\n1.The teams app or chat page need to be opened\n2.\n3.\n...\n```\n\n### Debug\n\n```markdown\nteams-for-linux --webDebug --logConfig='{}'\n```\n\n### Additional context\n\n![Image](https://github.com/user-attachments/assets/b7dcdfe7-aba2-46e7-b650-f642cb3f5622)\n\n![Image](https://github.com/user-attachments/assets/08bf96d6-6e8d-42c6-ba01-248fec3dbd99)",
    "state": "closed",
    "created_at": "2025-02-04T11:35:57+00:00",
    "updated_at": "2025-02-05T07:16:40+00:00",
    "closed_at": "2025-02-05T07:16:39+00:00",
    "user": "aravindhfinix",
    "assignee": "IsmaelMartinez",
    "labels": [
        "bug"
    ],
    "comments_count": 1,
    "html_url": "https://github.com/IsmaelMartinez/teams-for-linux/issues/1566",
    "is_pull_request": false
}