{
    "id": 2475213665,
    "number": 1369,
    "title": "Quits with `render-process-gone` when joining a call",
    "body": "**Describe the bug**\r\n\r\nQuits when joining a call with just `render-process-gone` and no other errors in the log. \r\n\r\nInterestingly, turning on `disableGpu` does not resolve this problem but makes the quits occur less often. Without `disableGpu` the app quits almost every time I try to join a call.\r\n\r\nMost likely related to https://github.com/electron/electron/issues/32760 where people suggest that a good workaround is adding `app.disableHardwareAcceleration()`. See https://github.com/electron/electron/issues/32760#issuecomment-2111717155.\r\n\r\nThis is currently not in effect when `disableGpu` is enabled. Can we introduce it and see if this helps?\r\n\r\nhttps://github.com/IsmaelMartinez/teams-for-linux/blob/fedf73ac4bdd1f4279c54f4f2f6e0c345e47faba/app/index.js#L124\r\n\r\n**To Reproduce**\r\n\r\nSteps to reproduce the behavior:\r\n\r\n1. Go to calendar\r\n2. Click _Meet now_ on the top or _Join_ on any of the events\r\n3. You don't get a chance to _Join now_ as the app quits when the screen with meeting controls loads\r\n\r\n**Expected behavior**\r\n\r\nCan join the call\r\n\r\n**Screenshots**\r\n\r\nn/a\r\n\r\n**Desktop (please complete the following information):**\r\n\r\n - OS: Arch\r\n - Installation package: https://aur.archlinux.org/packages/teams-for-linux\r\n - Version: 1.9.0-1\r\n\r\n**Debug**\r\n\r\n```\r\nall good with appLogLevels you aren't using them\r\nInitialising logger with config: \"{}\"\r\nLogger initialised with transports: {}\r\n11:36:48.131 › File logging at /home/greg/.config/teams-for-linux/logs/main.log with level silly\r\n11:36:48.132 › Console logging enabled with level silly\r\n11:36:48.132 › Logger initialised\r\n11:36:48.132 › configPath: /home/greg/.config/teams-for-linux\r\n11:36:48.133 › configFile: {\r\n  appIconType: 'light',\r\n  disableNotificationSound: true,\r\n  disableNotificationWindowFlash: true,\r\n  disableNotifications: true,\r\n  disableGpu: true,\r\n  followSystemTheme: true,\r\n  optInTeamsV2: true,\r\n  spellCheckerLanguages: [ 'en', 'pl' ]\r\n}\r\n11:36:48.135 › Running under Wayland, switching to PipeWire...\r\n11:36:48.135 › Disabling GPU support...\r\n11:36:48.372 › processArgs: [ '/opt/teams-for-linux/teams-for-linux' ]\r\n11:36:48.372 › testing RegExp processArgs false\r\n11:36:48.373 › Testing network using net.request() for https://teams.microsoft.com/v2\r\n11:36:48.374 › Language codes en,pl set for spellchecker\r\n11:36:48.626 › Network test successful with method https\r\n11:36:48.879 › GetSystemIdleState => IdleTimeout: 300s, IdleTimeoutPollInterval: 10s, ActiveCheckPollInterval: 2s, IdleTime: 0s, IdleState: 'active'\r\n11:36:49.376 › did-frame-finish-load {} true\r\n11:36:49.376 › did-finish-load\r\n11:36:50.613 › Badge count set to '0'\r\n11:36:50.623 › Badge count set to '0'\r\n11:36:51.367 › Badge count set to '0'\r\n11:36:53.029 › did-frame-finish-load {} false\r\n11:36:58.946 › GetSystemIdleState => IdleTimeout: 300s, IdleTimeoutPollInterval: 10s, ActiveCheckPollInterval: 2s, IdleTime: 0s, IdleState: 'active'\r\n11:37:07.929 › Badge count set to '0'\r\n11:37:08.233 › Badge count set to '0'\r\n11:37:08.804 › Badge count set to '0'\r\n11:37:09.196 › GetSystemIdleState => IdleTimeout: 300s, IdleTimeoutPollInterval: 10s, ActiveCheckPollInterval: 2s, IdleTime: 0s, IdleState: 'active'\r\n11:37:11.376 › Badge count set to '0'\r\n11:37:11.929 › render-process-gone\r\n11:37:11.929 › before-quit\r\n11:37:11.929 › window close\r\n11:37:11.932 › window closed\r\n11:37:11.932 › will-quit\r\n11:37:11.932 › quit\r\n```\r\n\r\n**Additional context**\r\n\r\nn/a\r\n",
    "state": "closed",
    "created_at": "2024-08-20T09:51:24+00:00",
    "updated_at": "2024-08-29T11:36:08+00:00",
    "closed_at": "2024-08-29T11:36:08+00:00",
    "user": "GrzegorzKozub",
    "assignee": null,
    "labels": [],
    "comments_count": 10,
    "html_url": "https://github.com/IsmaelMartinez/teams-for-linux/issues/1369",
    "is_pull_request": false
}